phylosophos/__init__.py
phylosophos/gbif_extra.py
phylosophos/phylosophos_core.py
phylosophos/phylosophos_initialize_update.py
phylosophos/ps_analysis.py
phylosophos/ps_initialize.py
phylosophos/ps_update.py
phylosophos-1.1.5.dist-info/LICENSE
phylosophos-1.1.5.dist-info/METADATA
phylosophos-1.1.5.dist-info/WHEEL
phylosophos-1.1.5.dist-info/top_level.txt
phylosophos-1.1.5.dist-info/RECORD
