Metadata-Version: 2.1
Name: phylosophos
Version: 1.1.5
Summary: PhyloSophos scientific name mapper
Home-page: https://github.com/mhcho4096/phylosophos
Author: Min Hyung Cho
Author-email: mhcho@bmdrc.org
License: MIT
Platform: UNKNOWN
Requires-Python: >=3.8
License-File: LICENSE
Requires-Dist: numpy
